libmedia_codec.cpython-38-x86_64-linux-gnu.so
robomaster-0.1.1.65.dist-info/WHEEL
robomaster-0.1.1.65.dist-info/zip-safe
robomaster-0.1.1.65.dist-info/LICENSE.txt
robomaster-0.1.1.65.dist-info/RECORD
robomaster-0.1.1.65.dist-info/METADATA
robomaster-0.1.1.65.dist-info/top_level.txt
multi_robomaster/multi_group.py
multi_robomaster/multi_robot.py
multi_robomaster/tool.py
multi_robomaster/__init__.py
multi_robomaster/multi_module.py
robomaster/gripper.py
robomaster/exceptions.py
robomaster/robotic_arm.py
robomaster/camera.py
robomaster/conn.py
robomaster/robot.py
robomaster/media.py
robomaster/servo.py
robomaster/__init__.py
robomaster/sensor.py
robomaster/action.py
robomaster/chassis.py
robomaster/armor.py
robomaster/blaster.py
robomaster/module.py
robomaster/dds.py
robomaster/config.py
robomaster/protocol.py
robomaster/util.py
robomaster/gimbal.py
robomaster/led.py
robomaster/battery.py
robomaster/client.py
robomaster/version.py
robomaster/vision.py
robomaster/uart.py
robomaster/algo.py
robomaster/flight.py
robomaster/event.py
robomaster.libs/libogg-24eaa32b.so.0.8.0
robomaster.libs/libavutil-a83d559d.so.54.20.100
robomaster.libs/libopus-abf1ee53.so.0.3.0
robomaster.libs/libvorbisenc-e32e3ab5.so.2.0.9
robomaster.libs/libswscale-ae22abec.so.3.1.101
robomaster.libs/libtheoraenc-b005fd1d.so.1.1.2
robomaster.libs/libz-d8a329de.so.1.2.7
robomaster.libs/libva-cc18982b.so.1.4000.0
robomaster.libs/libtheoradec-c1ea91f0.so.1.1.4
robomaster.libs/libavcodec-70240708.so.56.26.100
robomaster.libs/libvorbis-02341991.so.0.4.6
