Metadata-Version: 2.1
Name: robomaster
Version: 0.1.1.65
Summary: RoboMaster Python SDK
Home-page: http://www.robomaster.com
Author: EDU SDK TEAM
License: Apache License, Version 2.0
Keywords: dji,robomaster,sdk,robot,drone
Platform: UNKNOWN
Requires-Dist: numpy (>=1.18)
Requires-Dist: opencv-python (>=4.2)
Requires-Dist: netaddr (>=0.8)
Requires-Dist: netifaces (>=0.10)
Requires-Dist: myqr (>=2.3)
